pytdo/__init__.py
pytdo/__main__.py
pytdo/assets/config_default.toml
pytdo/config/__init__.py
pytdo/config/_config.py
pytdo/config/_types.py
pytdo/config/models.py
pytdo/gui/__init__.py
pytdo/gui/_core.py
pytdo/gui/_workers.py
pytdo/gui/widgets/__init__.py
pytdo/gui/widgets/_configuration_tab.py
pytdo/gui/widgets/_graphs.py
pytdo/gui/widgets/_main_buttons.py
pytdo/gui/widgets/_param_content.py
pytdo/processors/__init__.py
pytdo/processors/_tdo.py
pytdo/processors/_types.py
pytdo/py.typed
pytdo/sp.py
pytdo-0.2.11.dist-info/WHEEL
pytdo-0.2.11.dist-info/entry_points.txt
pytdo-0.2.11.dist-info/METADATA
pytdo-0.2.11.dist-info/RECORD
