Metadata-Version: 2.3
Name: pytdo
Version: 0.2.11
Summary: Add your description here
Author: Guillaume Le Goc
Author-email: Guillaume Le Goc <guillaume.le-goc@lncmi.cnrs.fr>
Requires-Dist: matplotlib>=3.10.7
Requires-Dist: numpy>=2.3.5
Requires-Dist: rich>=14.2.0
Requires-Dist: scipy>=1.16.3
Requires-Dist: pydantic>=2.12.4
Requires-Dist: pyqt6>=6.10.0
Requires-Dist: pyuson>=0.7.5
Requires-Python: >=3.12
